light_compressor/__init__.py
light_compressor/compressor_method.py
light_compressor/reader.py
light_compressor/writer.py
light_compressor/compressors/__init__.py
light_compressor/compressors/lz4.cp310-win_amd64.pyd
light_compressor/compressors/lz4.pxd
light_compressor/compressors/lz4.pyi
light_compressor/compressors/lz4.pyx
light_compressor/compressors/zstd.cp310-win_amd64.pyd
light_compressor/compressors/zstd.pxd
light_compressor/compressors/zstd.pyi
light_compressor/compressors/zstd.pyx
light_compressor/decompressors/__init__.py
light_compressor/decompressors/decompress_reader.py
light_compressor/decompressors/lz4.cp310-win_amd64.pyd
light_compressor/decompressors/lz4.pxd
light_compressor/decompressors/lz4.pyi
light_compressor/decompressors/lz4.pyx
light_compressor/decompressors/zstd.cp310-win_amd64.pyd
light_compressor/decompressors/zstd.pxd
light_compressor/decompressors/zstd.pyi
light_compressor/decompressors/zstd.pyx
light_compressor-0.0.2.1.dist-info/licenses/LICENSE
light_compressor-0.0.2.1.dist-info/METADATA
light_compressor-0.0.2.1.dist-info/WHEEL
light_compressor-0.0.2.1.dist-info/top_level.txt
light_compressor-0.0.2.1.dist-info/RECORD
