Metadata-Version: 2.4
Name: light_compressor
Version: 0.0.2.1
Summary: Library for read compressed stream and write compressed chunks.
Author-email: 0xMihalich <bayanmobile87@gmail.com>
License: MIT License
Project-URL: Homepage, https://github.com/0xMihalich/light_compressor
Project-URL: Documentation, https://github.com/0xMihalich/light_compressor#readme
Project-URL: Repository, https://github.com/0xMihalich/light_compressor
Project-URL: Changelog, https://github.com/0xMihalich/light_compressor/blob/main/CHANGELOG.md
Classifier: Development Status :: 4 - Beta
Classifier: Intended Audience :: Developers
Classifier: Programming Language :: Python :: 3.10
Classifier: Programming Language :: Python :: 3.11
Classifier: Programming Language :: Python :: 3.12
Classifier: Programming Language :: Python :: 3.13
Classifier: Programming Language :: Python :: 3.14
Requires-Python: >=3.10
License-File: LICENSE
Requires-Dist: cffi>=1.17.1
Requires-Dist: lz4>=4.4.3
Requires-Dist: zstandard>=0.23.0
Dynamic: license-file
